fastapi_errors/__init__.py
fastapi_errors/exceptions.py
fastapi_errors/generator.py
fastapi_errors-0.0.6.dist-info/LICENSE
fastapi_errors-0.0.6.dist-info/WHEEL
fastapi_errors-0.0.6.dist-info/METADATA
fastapi_errors-0.0.6.dist-info/RECORD
