Metadata-Version: 2.1
Name: fastapi_errors
Version: 0.0.6
Summary: Fastapi errors module.
Author-email: Rey092 <roman.cheburan@gmail.com>
Classifier: License :: OSI Approved :: MIT License
